{
  "timestamp": 1774465656597,
  "lastUpdated": "2026-03-25T19:07:36.597Z",
  "servers": {
    "caucasus": {
      "server": "caucasus",
      "serverName": "101 Hunter SQN | Caucasus | Server",
      "theatre": "Caucasus",
      "playerCount": 0,
      "missionTime": 14718,
      "timestamp": 1774465655,
      "units": [
        {
          "name": "Aerial-7-1",
          "aircraft": "Su-27",
          "lat": 44.051989,
          "lon": 38.932707,
          "alt": 3048,
          "heading": 139.8,
          "speed": 376.9,
          "coalition": "neutral",
          "unitType": "aircraft",
          "isPlayer": false
        },
        {
          "name": "A/A S27-1",
          "aircraft": "Su-27",
          "lat": 44.050839,
          "lon": 38.917609,
          "alt": 3048,
          "heading": 139.8,
          "speed": 377.1,
          "coalition": "neutral",
          "unitType": "aircraft",
          "isPlayer": false
        },
        {
          "name": "A/A S27-2",
          "aircraft": "Su-27",
          "lat": 44.049682,
          "lon": 38.902517,
          "alt": 3048,
          "heading": 139.8,
          "speed": 377,
          "coalition": "neutral",
          "unitType": "aircraft",
          "isPlayer": false
        },
        {
          "name": "A/A S27-3",
          "aircraft": "Su-27",
          "lat": 44.048538,
          "lon": 38.887409,
          "alt": 3049,
          "heading": 139.8,
          "speed": 377.2,
          "coalition": "neutral",
          "unitType": "aircraft",
          "isPlayer": false
        },
        {
          "name": "A/A S27-1-1",
          "aircraft": "Su-27",
          "lat": 44.083225,
          "lon": 38.912237,
          "alt": 3048,
          "heading": 139.2,
          "speed": 376.7,
          "coalition": "neutral",
          "unitType": "aircraft",
          "isPlayer": false
        },
        {
          "name": "A/A S27-1-2",
          "aircraft": "Su-27",
          "lat": 44.081965,
          "lon": 38.897147,
          "alt": 3048,
          "heading": 139.2,
          "speed": 376.8,
          "coalition": "neutral",
          "unitType": "aircraft",
          "isPlayer": false
        },
        {
          "name": "A/A S27-1-3",
          "aircraft": "Su-27",
          "lat": 44.080695,
          "lon": 38.882064,
          "alt": 3048,
          "heading": 139.2,
          "speed": 376.8,
          "coalition": "neutral",
          "unitType": "aircraft",
          "isPlayer": false
        },
        {
          "name": "A/A S27-1-4",
          "aircraft": "Su-27",
          "lat": 44.079423,
          "lon": 38.866982,
          "alt": 3047,
          "heading": 139.2,
          "speed": 376.3,
          "coalition": "neutral",
          "unitType": "aircraft",
          "isPlayer": false
        },
        {
          "name": "A/A S27-2-1",
          "aircraft": "Su-27",
          "lat": 44.128858,
          "lon": 38.892121,
          "alt": 3048,
          "heading": 138.4,
          "speed": 376.3,
          "coalition": "neutral",
          "unitType": "aircraft",
          "isPlayer": false
        },
        {
          "name": "A/A S27-2-2",
          "aircraft": "Su-27",
          "lat": 44.127453,
          "lon": 38.877027,
          "alt": 3048,
          "heading": 138.4,
          "speed": 377.8,
          "coalition": "neutral",
          "unitType": "aircraft",
          "isPlayer": false
        },
        {
          "name": "Aerial-9-3",
          "aircraft": "KC135MPRS",
          "lat": 43.719394,
          "lon": 37.442457,
          "alt": 6704,
          "heading": 59,
          "speed": 435,
          "coalition": "neutral",
          "unitType": "aircraft",
          "isPlayer": false
        },
        {
          "name": "A/A S27-2-3",
          "aircraft": "Su-27",
          "lat": 44.126034,
          "lon": 38.861947,
          "alt": 3048,
          "heading": 138.4,
          "speed": 379.9,
          "coalition": "neutral",
          "unitType": "aircraft",
          "isPlayer": false
        },
        {
          "name": "Aerial-2-3",
          "aircraft": "IL-78M",
          "lat": 44.427205,
          "lon": 37.162519,
          "alt": 6706,
          "heading": 318.4,
          "speed": 432.5,
          "coalition": "neutral",
          "unitType": "aircraft",
          "isPlayer": false
        },
        {
          "name": "Aerial-5-1",
          "aircraft": "KC-135",
          "lat": 44.294624,
          "lon": 37.655715,
          "alt": 6706,
          "heading": 317.8,
          "speed": 530,
          "coalition": "neutral",
          "unitType": "aircraft",
          "isPlayer": false
        },
        {
          "name": "Aerial-3-1",
          "aircraft": "KJ-2000",
          "lat": 42.453451,
          "lon": 43.919225,
          "alt": 10732,
          "heading": 216.9,
          "speed": 406.5,
          "coalition": "neutral",
          "unitType": "aircraft",
          "isPlayer": false
        },
        {
          "name": "Aerial-1-1",
          "aircraft": "E-3A",
          "lat": 42.382852,
          "lon": 43.517786,
          "alt": 10668,
          "heading": 357,
          "speed": 433.3,
          "coalition": "neutral",
          "unitType": "aircraft",
          "isPlayer": false
        },
        {
          "name": "A/A S27-2-4",
          "aircraft": "Su-27",
          "lat": 44.124616,
          "lon": 38.846857,
          "alt": 3050,
          "heading": 138.3,
          "speed": 382.7,
          "coalition": "neutral",
          "unitType": "aircraft",
          "isPlayer": false
        },
        {
          "name": "Aerial-7-2",
          "aircraft": "E-3A",
          "lat": 43.700566,
          "lon": 41.993463,
          "alt": 10670,
          "heading": 176.3,
          "speed": 379.7,
          "coalition": "neutral",
          "unitType": "aircraft",
          "isPlayer": false
        },
        {
          "name": "Aerial-8-1",
          "aircraft": "KJ-2000",
          "lat": 43.720987,
          "lon": 42.14134,
          "alt": 11522,
          "heading": 233.6,
          "speed": 362.8,
          "coalition": "neutral",
          "unitType": "aircraft",
          "isPlayer": false
        },
        {
          "name": "A/A S27-3-1",
          "aircraft": "F-16C_50",
          "lat": 41.976087,
          "lon": 40.75564,
          "alt": 3050,
          "heading": 261.5,
          "speed": 517.6,
          "coalition": "neutral",
          "unitType": "aircraft",
          "isPlayer": false
        },
        {
          "name": "A/A S27-3-2",
          "aircraft": "F-16C_50",
          "lat": 41.979756,
          "lon": 40.758518,
          "alt": 3049,
          "heading": 261.7,
          "speed": 492.5,
          "coalition": "neutral",
          "unitType": "aircraft",
          "isPlayer": false
        },
        {
          "name": "A/A S27-3-3",
          "aircraft": "F-16C_50",
          "lat": 41.984195,
          "lon": 40.763038,
          "alt": 3047,
          "heading": 259.8,
          "speed": 537.9,
          "coalition": "neutral",
          "unitType": "aircraft",
          "isPlayer": false
        },
        {
          "name": "A/A S27-3-4",
          "aircraft": "F-16C_50",
          "lat": 41.999974,
          "lon": 40.788018,
          "alt": 3031,
          "heading": 222.9,
          "speed": 578.3,
          "coalition": "neutral",
          "unitType": "aircraft",
          "isPlayer": false
        },
        {
          "name": "Rotary-1-1",
          "aircraft": "Ka-50_3",
          "lat": 43.406649,
          "lon": 40.045207,
          "alt": 122,
          "heading": 186.2,
          "speed": 20.1,
          "coalition": "neutral",
          "unitType": "helicopter",
          "isPlayer": false
        },
        {
          "name": "Rotary-1-2",
          "aircraft": "Ka-50_3",
          "lat": 43.407022,
          "lon": 40.045843,
          "alt": 124,
          "heading": 186.9,
          "speed": 18.4,
          "coalition": "neutral",
          "unitType": "helicopter",
          "isPlayer": false
        },
        {
          "name": "S3-1-1",
          "aircraft": "S-3B Tanker",
          "lat": 43.275966,
          "lon": 37.921979,
          "alt": 1829,
          "heading": 302.6,
          "speed": 253.8,
          "coalition": "neutral",
          "unitType": "aircraft",
          "isPlayer": false
        },
        {
          "name": "S3-1",
          "aircraft": "S-3B Tanker",
          "lat": 43.571622,
          "lon": 38.376435,
          "alt": 1829,
          "heading": 302.6,
          "speed": 253.8,
          "coalition": "neutral",
          "unitType": "aircraft",
          "isPlayer": false
        }
      ],
      "serverId": "caucasus",
      "online": true
    },
    "syria": {
      "server": "syria",
      "serverName": "101 Hunter SQN | Syria | Server",
      "theatre": "Syria",
      "playerCount": 1,
      "missionTime": 14533,
      "timestamp": 1774465655,
      "units": [
        {
          "name": "Aerial-6-1",
          "aircraft": "E-3A",
          "lat": 32.548666,
          "lon": 37.619645,
          "alt": 11717,
          "heading": 124.3,
          "speed": 371,
          "coalition": "neutral",
          "unitType": "aircraft",
          "isPlayer": false
        },
        {
          "name": "Aerial-10-1",
          "aircraft": "F-15C",
          "lat": 36.408466,
          "lon": 36.429324,
          "alt": 4571,
          "heading": 233.7,
          "speed": 438.1,
          "coalition": "neutral",
          "unitType": "aircraft",
          "isPlayer": false
        },
        {
          "name": "Aerial-10-2",
          "aircraft": "F-15C",
          "lat": 36.414743,
          "lon": 36.441201,
          "alt": 4567,
          "heading": 240.3,
          "speed": 388.8,
          "coalition": "neutral",
          "unitType": "aircraft",
          "isPlayer": false
        },
        {
          "name": "Aerial-10-3",
          "aircraft": "F-15C",
          "lat": 36.425711,
          "lon": 36.461665,
          "alt": 4564,
          "heading": 266.6,
          "speed": 489.5,
          "coalition": "neutral",
          "unitType": "aircraft",
          "isPlayer": false
        },
        {
          "name": "Aerial-10-4",
          "aircraft": "F-15C",
          "lat": 36.422866,
          "lon": 36.497929,
          "alt": 4557,
          "heading": 297.8,
          "speed": 518,
          "coalition": "neutral",
          "unitType": "aircraft",
          "isPlayer": false
        },
        {
          "name": "A-A ZONE-1-1",
          "aircraft": "F-15C",
          "lat": 36.385843,
          "lon": 36.423847,
          "alt": 4571,
          "heading": 233.7,
          "speed": 438.1,
          "coalition": "neutral",
          "unitType": "aircraft",
          "isPlayer": false
        },
        {
          "name": "A-A ZONE-1-2",
          "aircraft": "F-15C",
          "lat": 36.394141,
          "lon": 36.436068,
          "alt": 4557,
          "heading": 256.3,
          "speed": 351,
          "coalition": "neutral",
          "unitType": "aircraft",
          "isPlayer": false
        },
        {
          "name": "A-A ZONE-1-3",
          "aircraft": "F-15C",
          "lat": 36.405785,
          "lon": 36.453481,
          "alt": 4571,
          "heading": 256.1,
          "speed": 498.2,
          "coalition": "neutral",
          "unitType": "aircraft",
          "isPlayer": false
        },
        {
          "name": "A-A ZONE-1-4",
          "aircraft": "F-15C",
          "lat": 36.411019,
          "lon": 36.485946,
          "alt": 4556,
          "heading": 292.9,
          "speed": 513.2,
          "coalition": "neutral",
          "unitType": "aircraft",
          "isPlayer": false
        },
        {
          "name": "A-A ZONE-2-1",
          "aircraft": "F-15C",
          "lat": 36.384456,
          "lon": 36.453431,
          "alt": 4573,
          "heading": 246.2,
          "speed": 437.2,
          "coalition": "neutral",
          "unitType": "aircraft",
          "isPlayer": false
        },
        {
          "name": "A-A ZONE-2-2",
          "aircraft": "F-15C",
          "lat": 36.388225,
          "lon": 36.466093,
          "alt": 4572,
          "heading": 246.6,
          "speed": 440.7,
          "coalition": "neutral",
          "unitType": "aircraft",
          "isPlayer": false
        },
        {
          "name": "A-A ZONE-2-3",
          "aircraft": "F-15C",
          "lat": 36.387481,
          "lon": 36.494309,
          "alt": 4564,
          "heading": 285.8,
          "speed": 513.8,
          "coalition": "neutral",
          "unitType": "aircraft",
          "isPlayer": false
        },
        {
          "name": "A-A ZONE-2-4",
          "aircraft": "F-15C",
          "lat": 36.381484,
          "lon": 36.538331,
          "alt": 4571,
          "heading": 293.7,
          "speed": 508.3,
          "coalition": "neutral",
          "unitType": "aircraft",
          "isPlayer": false
        },
        {
          "name": "A-A ZONE-3-2",
          "aircraft": "F-15C",
          "lat": 36.26942,
          "lon": 36.257528,
          "alt": 4576,
          "heading": 88.6,
          "speed": 459.3,
          "coalition": "neutral",
          "unitType": "aircraft",
          "isPlayer": false
        },
        {
          "name": "A-A ZONE-3-3",
          "aircraft": "F-15C",
          "lat": 36.259645,
          "lon": 36.251414,
          "alt": 4575,
          "heading": 88.6,
          "speed": 457.4,
          "coalition": "neutral",
          "unitType": "aircraft",
          "isPlayer": false
        },
        {
          "name": "A-A ZONE-4-1",
          "aircraft": "F-15C",
          "lat": 36.258271,
          "lon": 36.481659,
          "alt": 4576,
          "heading": 85.7,
          "speed": 459.5,
          "coalition": "neutral",
          "unitType": "aircraft",
          "isPlayer": false
        },
        {
          "name": "A-A ZONE-4-3",
          "aircraft": "F-15C",
          "lat": 36.248253,
          "lon": 36.476088,
          "alt": 4574,
          "heading": 85.7,
          "speed": 459.1,
          "coalition": "neutral",
          "unitType": "aircraft",
          "isPlayer": false
        },
        {
          "name": "A-A ZONE-4-4",
          "aircraft": "F-15C",
          "lat": 36.228217,
          "lon": 36.464961,
          "alt": 4574,
          "heading": 85.7,
          "speed": 459.5,
          "coalition": "neutral",
          "unitType": "aircraft",
          "isPlayer": false
        },
        {
          "name": "Aerial-30-1",
          "aircraft": "KJ-2000",
          "lat": 32.828892,
          "lon": 33.076512,
          "alt": 12111,
          "heading": 233.5,
          "speed": 417.1,
          "coalition": "neutral",
          "unitType": "aircraft",
          "isPlayer": false
        },
        {
          "name": "Aerial-31-1",
          "aircraft": "E-3A",
          "lat": 32.738062,
          "lon": 33.025437,
          "alt": 10720,
          "heading": 28.9,
          "speed": 439.7,
          "coalition": "neutral",
          "unitType": "aircraft",
          "isPlayer": false
        },
        {
          "name": "A-A ZONE-5-1",
          "aircraft": "F-16C_50",
          "lat": 34.948441,
          "lon": 32.684264,
          "alt": 4576,
          "heading": 280.8,
          "speed": 417.2,
          "coalition": "neutral",
          "unitType": "aircraft",
          "isPlayer": false
        },
        {
          "name": "A-A ZONE-5-2",
          "aircraft": "F-16C_50",
          "lat": 34.957143,
          "lon": 32.692299,
          "alt": 4575,
          "heading": 280.8,
          "speed": 417.3,
          "coalition": "neutral",
          "unitType": "aircraft",
          "isPlayer": false
        },
        {
          "name": "A-A ZONE-5-3",
          "aircraft": "F-16C_50",
          "lat": 34.965845,
          "lon": 32.700327,
          "alt": 4575,
          "heading": 280.8,
          "speed": 417,
          "coalition": "neutral",
          "unitType": "aircraft",
          "isPlayer": false
        },
        {
          "name": "A-A ZONE-5-4",
          "aircraft": "F-16C_50",
          "lat": 34.974536,
          "lon": 32.708363,
          "alt": 4576,
          "heading": 280.8,
          "speed": 417.4,
          "coalition": "neutral",
          "unitType": "aircraft",
          "isPlayer": false
        },
        {
          "name": "Aerial-1-3",
          "aircraft": "KC-135",
          "lat": 36.437807,
          "lon": 34.185895,
          "alt": 7620,
          "heading": 37.4,
          "speed": 445,
          "coalition": "neutral",
          "unitType": "aircraft",
          "isPlayer": false
        },
        {
          "name": "Aerial-2-2",
          "aircraft": "KC135MPRS",
          "lat": 36.309095,
          "lon": 34.040095,
          "alt": 7621,
          "heading": 149.1,
          "speed": 447.6,
          "coalition": "neutral",
          "unitType": "aircraft",
          "isPlayer": false
        },
        {
          "name": "Aerial-3-1",
          "aircraft": "KJ-2000",
          "lat": 34.789779,
          "lon": 37.326975,
          "alt": 11074,
          "heading": 347.8,
          "speed": 427.5,
          "coalition": "neutral",
          "unitType": "aircraft",
          "isPlayer": false
        },
        {
          "name": "Aerial-4-1",
          "aircraft": "E-3A",
          "lat": 34.826453,
          "lon": 37.836736,
          "alt": 11151,
          "heading": 170.2,
          "speed": 394.1,
          "coalition": "neutral",
          "unitType": "aircraft",
          "isPlayer": false
        },
        {
          "name": "Aerial-27-1",
          "aircraft": "B-52H",
          "lat": 36.682652,
          "lon": 35.372575,
          "alt": 2196,
          "heading": 55.7,
          "speed": 272.5,
          "coalition": "neutral",
          "unitType": "aircraft",
          "isPlayer": false
        },
        {
          "name": "Aerial-27-2",
          "aircraft": "B-52H",
          "lat": 36.66143,
          "lon": 35.335832,
          "alt": 2184,
          "heading": 57.1,
          "speed": 292.9,
          "coalition": "neutral",
          "unitType": "aircraft",
          "isPlayer": false
        },
        {
          "name": "Aerial-27-3",
          "aircraft": "B-52H",
          "lat": 36.641015,
          "lon": 35.294432,
          "alt": 2173,
          "heading": 60.7,
          "speed": 318.1,
          "coalition": "neutral",
          "unitType": "aircraft",
          "isPlayer": false
        },
        {
          "name": "Aerial-28-1",
          "aircraft": "E-3A",
          "lat": 36.077082,
          "lon": 34.185148,
          "alt": 10715,
          "heading": 46.8,
          "speed": 447.3,
          "coalition": "neutral",
          "unitType": "aircraft",
          "isPlayer": false
        },
        {
          "name": "Aerial-29-1",
          "aircraft": "KJ-2000",
          "lat": 36.152142,
          "lon": 34.655154,
          "alt": 12192,
          "heading": 66.4,
          "speed": 465.5,
          "coalition": "neutral",
          "unitType": "aircraft",
          "isPlayer": false
        },
        {
          "name": "Aerial-5-1",
          "aircraft": "KJ-2000",
          "lat": 32.546199,
          "lon": 37.273383,
          "alt": 10711,
          "heading": 50.9,
          "speed": 464.6,
          "coalition": "neutral",
          "unitType": "aircraft",
          "isPlayer": false
        },
        {
          "name": "CanAda",
          "aircraft": "FA-18C_hornet",
          "lat": 36.686463,
          "lon": 34.996392,
          "alt": 1212,
          "heading": 232,
          "speed": 387.9,
          "coalition": "neutral",
          "unitType": "aircraft",
          "isPlayer": true
        }
      ],
      "serverId": "syria",
      "online": true
    },
    "syria-edc": {
      "server": "syria",
      "serverName": "101 Hunter SQN | Syria EDC",
      "theatre": "Syria",
      "playerCount": 1,
      "missionTime": 14286,
      "timestamp": 1774465655,
      "units": [
        {
          "name": "DYNH-Tabqa-Military_Base-cap_attack-046-02",
          "aircraft": "F-15C",
          "lat": 35.755133,
          "lon": 38.556442,
          "alt": 337,
          "heading": 273.2,
          "speed": 26.5,
          "coalition": "neutral",
          "unitType": "aircraft",
          "isPlayer": false
        },
        {
          "name": "DYNH-Palmyra-Hama-cap_attack-032-01",
          "aircraft": "MiG-29 Fulcrum",
          "lat": 34.749833,
          "lon": 37.724104,
          "alt": 6580,
          "heading": 39.4,
          "speed": 497.4,
          "coalition": "neutral",
          "unitType": "aircraft",
          "isPlayer": false
        },
        {
          "name": "DYNH-Palmyra-Hama-cap_attack-032-02",
          "aircraft": "MiG-29 Fulcrum",
          "lat": 34.56157,
          "lon": 37.772582,
          "alt": 1065,
          "heading": 208.5,
          "speed": 356.5,
          "coalition": "neutral",
          "unitType": "aircraft",
          "isPlayer": false
        },
        {
          "name": "escort-me-01",
          "aircraft": "C-130",
          "lat": 37.002841,
          "lon": 35.422797,
          "alt": 56,
          "heading": 55,
          "speed": 16.2,
          "coalition": "neutral",
          "unitType": "aircraft",
          "isPlayer": false
        },
        {
          "name": "AWACS_RED-1",
          "aircraft": "A-50",
          "lat": 32.080132,
          "lon": 34.963098,
          "alt": 9144,
          "heading": 8.9,
          "speed": 456.2,
          "coalition": "neutral",
          "unitType": "aircraft",
          "isPlayer": false
        },
        {
          "name": "EscortBomber-02",
          "aircraft": "MiG-29S",
          "lat": 37.445938,
          "lon": 38.903991,
          "alt": 825,
          "heading": 131.1,
          "speed": 0,
          "coalition": "neutral",
          "unitType": "aircraft",
          "isPlayer": false
        },
        {
          "name": "Palmyra-patrol-Palmyra-Cap-02",
          "aircraft": "MiG-25PD",
          "lat": 34.385595,
          "lon": 38.008354,
          "alt": 7309,
          "heading": 249.2,
          "speed": 459.1,
          "coalition": "neutral",
          "unitType": "aircraft",
          "isPlayer": false
        },
        {
          "name": "Palmyra-patrol-Palmyra-Cap-01",
          "aircraft": "MiG-25PD",
          "lat": 34.373074,
          "lon": 38.000061,
          "alt": 7315,
          "heading": 242.9,
          "speed": 461.6,
          "coalition": "neutral",
          "unitType": "aircraft",
          "isPlayer": false
        },
        {
          "name": "Jirah-patrol-Hama-Cap-02",
          "aircraft": "F-15C",
          "lat": 34.91961,
          "lon": 36.899641,
          "alt": 6776,
          "heading": 289.7,
          "speed": 499.8,
          "coalition": "neutral",
          "unitType": "aircraft",
          "isPlayer": false
        },
        {
          "name": "AWACS_BLUE-1",
          "aircraft": "E-3A",
          "lat": 35.667926,
          "lon": 36.75133,
          "alt": 9144,
          "heading": 327.8,
          "speed": 461.4,
          "coalition": "neutral",
          "unitType": "aircraft",
          "isPlayer": false
        },
        {
          "name": "Jirah-patrol-Hama-Cap-01",
          "aircraft": "F-15C",
          "lat": 34.932416,
          "lon": 36.889623,
          "alt": 7009,
          "heading": 289.7,
          "speed": 456.7,
          "coalition": "neutral",
          "unitType": "aircraft",
          "isPlayer": false
        },
        {
          "name": "AWACS_BLUE_SECONDARY",
          "aircraft": "E-3A",
          "lat": 36.028586,
          "lon": 38.763904,
          "alt": 9144,
          "heading": 10.6,
          "speed": 474.6,
          "coalition": "neutral",
          "unitType": "aircraft",
          "isPlayer": false
        },
        {
          "name": "EscortBomber-01",
          "aircraft": "MiG-29S",
          "lat": 37.446344,
          "lon": 38.904303,
          "alt": 825,
          "heading": 132,
          "speed": 0,
          "coalition": "neutral",
          "unitType": "aircraft",
          "isPlayer": false
        },
        {
          "name": "101-Tunay [5555]",
          "aircraft": "F-16C_50",
          "lat": 35.596112,
          "lon": 38.595488,
          "alt": 2812,
          "heading": 52.6,
          "speed": 521.5,
          "coalition": "neutral",
          "unitType": "aircraft",
          "isPlayer": false
        }
      ],
      "serverId": "syria-edc",
      "online": true
    },
    "caucasus-edc": {
      "server": "caucasus",
      "serverName": "101 Hunter SQN | Caucasus EDC",
      "theatre": "Caucasus",
      "playerCount": 1,
      "missionTime": 14167,
      "timestamp": 1774465655,
      "units": [
        {
          "name": "Carrier Blue Tanker",
          "aircraft": "S-3B Tanker",
          "lat": 41.962258,
          "lon": 41.055762,
          "alt": 2441,
          "heading": 126.5,
          "speed": 341.3,
          "coalition": "neutral",
          "unitType": "aircraft",
          "isPlayer": false
        },
        {
          "name": "Sukhumi-supply-alpha-01",
          "aircraft": "Mi-8MT",
          "lat": 42.868881,
          "lon": 41.120407,
          "alt": 45,
          "heading": 179.8,
          "speed": 17.6,
          "coalition": "neutral",
          "unitType": "helicopter",
          "isPlayer": false
        },
        {
          "name": "EscortBomber-01",
          "aircraft": "MiG-29S",
          "lat": 45.02735,
          "lon": 43.352294,
          "alt": 4820,
          "heading": 177.8,
          "speed": 428.3,
          "coalition": "neutral",
          "unitType": "aircraft",
          "isPlayer": false
        },
        {
          "name": "Sukhumi-patrol-Alpha-02",
          "aircraft": "MiG-29S",
          "lat": 42.870143,
          "lon": 41.111316,
          "alt": 15,
          "heading": 107.5,
          "speed": 16.1,
          "coalition": "neutral",
          "unitType": "aircraft",
          "isPlayer": false
        },
        {
          "name": "Sukhumi-patrol-Alpha-01",
          "aircraft": "MiG-29S",
          "lat": 42.868876,
          "lon": 41.125112,
          "alt": 15,
          "heading": 357.2,
          "speed": 3.9,
          "coalition": "neutral",
          "unitType": "aircraft",
          "isPlayer": false
        },
        {
          "name": "EscortBomber-02",
          "aircraft": "MiG-29S",
          "lat": 45.029695,
          "lon": 43.351946,
          "alt": 4768,
          "heading": 177.8,
          "speed": 428.8,
          "coalition": "neutral",
          "unitType": "aircraft",
          "isPlayer": false
        },
        {
          "name": "AWACS_BLUE",
          "aircraft": "E-3A",
          "lat": 41.829232,
          "lon": 40.938572,
          "alt": 9144,
          "heading": 28.4,
          "speed": 497.7,
          "coalition": "neutral",
          "unitType": "aircraft",
          "isPlayer": false
        },
        {
          "name": "AWACS_RED",
          "aircraft": "A-50",
          "lat": 43.664343,
          "lon": 45.185003,
          "alt": 9144,
          "heading": 351.9,
          "speed": 483.8,
          "coalition": "neutral",
          "unitType": "aircraft",
          "isPlayer": false
        },
        {
          "name": "carrier-patrol-Kobuleti-01",
          "aircraft": "F-14B",
          "lat": 42.004324,
          "lon": 41.994,
          "alt": 7010,
          "heading": 22.5,
          "speed": 508.5,
          "coalition": "neutral",
          "unitType": "aircraft",
          "isPlayer": false
        },
        {
          "name": "Ibraki",
          "aircraft": "TF-51D",
          "lat": 41.927866,
          "lon": 41.863346,
          "alt": 20,
          "heading": 339.9,
          "speed": 0,
          "coalition": "neutral",
          "unitType": "unknown",
          "isPlayer": true
        },
        {
          "name": "carrier-patrol-Kobuleti-02",
          "aircraft": "F-14B",
          "lat": 42.033132,
          "lon": 41.857278,
          "alt": 5913,
          "heading": 120.1,
          "speed": 494.4,
          "coalition": "neutral",
          "unitType": "aircraft",
          "isPlayer": false
        },
        {
          "name": "Kutaisi-attack-Sukhumi-01",
          "aircraft": "F-15C",
          "lat": 42.282491,
          "lon": 42.015684,
          "alt": 8228,
          "heading": 110.7,
          "speed": 458.8,
          "coalition": "neutral",
          "unitType": "aircraft",
          "isPlayer": false
        },
        {
          "name": "Kutaisi-attack-Sukhumi-02",
          "aircraft": "F-15C",
          "lat": 42.289883,
          "lon": 41.984435,
          "alt": 7869,
          "heading": 127.9,
          "speed": 501.1,
          "coalition": "neutral",
          "unitType": "aircraft",
          "isPlayer": false
        }
      ],
      "serverId": "caucasus-edc",
      "online": true
    }
  },
  "totalPlayers": 3,
  "activeServers": 4
}